[
  {
    "trend_arrow": "45_DOWN", 
    "display_time": "2016-06-16T04:08:03-07:00", 
    "system_time": "2016-06-16T10:05:27-07:00", 
    "direction": "FortyFiveDown", 
    "sgv": 119, 
    "dateString": "2016-06-16T04:08:03-07:00", 
    "device": "openaps://cgm", 
    "unfiltered": 148032, 
    "rssi": 192, 
    "date": 1466075283000, 
    "filtered": 155232, 
    "type": "sgv", 
    "glucose": 119
  }, 
  {
    "trend_arrow": "45_DOWN", 
    "display_time": "2016-06-16T04:03:02-07:00", 
    "system_time": "2016-06-16T10:00:27-07:00", 
    "direction": "FortyFiveDown", 
    "sgv": 123, 
    "dateString": "2016-06-16T04:03:02-07:00", 
    "device": "openaps://cgm", 
    "unfiltered": 153888, 
    "rssi": 193, 
    "date": 1466074982000, 
    "filtered": 159264, 
    "type": "sgv", 
    "glucose": 123
  }, 
  {
    "trend_arrow": "FLAT", 
    "display_time": "2016-06-16T04:23:03-07:00", 
    "system_time": "2016-06-16T10:20:27-07:00", 
    "direction": "Flat", 
    "sgv": 106, 
    "dateString": "2016-06-16T04:23:03-07:00", 
    "device": "openaps://cgm", 
    "unfiltered": 132544, 
    "rssi": 434, 
    "date": 1466076183000, 
    "filtered": 137856, 
    "type": "sgv", 
    "glucose": 106
  }, 
  {
    "trend_arrow": "FLAT", 
    "display_time": "2016-06-16T04:18:02-07:00", 
    "system_time": "2016-06-16T10:15:27-07:00", 
    "direction": "Flat", 
    "sgv": 110, 
    "dateString": "2016-06-16T04:18:02-07:00", 
    "device": "openaps://cgm", 
    "unfiltered": 135264, 
    "rssi": 186, 
    "date": 1466075882000, 
    "filtered": 144192, 
    "type": "sgv", 
    "glucose": 110
  }, 
  {
    "trend_arrow": "FLAT", 
    "display_time": "2016-06-16T07:23:02-07:00", 
    "system_time": "2016-06-16T13:20:26-07:00", 
    "direction": "Flat", 
    "sgv": 118, 
    "dateString": "2016-06-16T07:23:02-07:00", 
    "device": "openaps://cgm", 
    "unfiltered": 121072, 
    "rssi": 197, 
    "date": 1466086982000, 
    "filtered": 118400, 
    "type": "sgv", 
    "glucose": 118
  }, 
  {
    "trend_arrow": "FLAT", 
    "display_time": "2016-06-16T07:18:01-07:00", 
    "system_time": "2016-06-16T13:15:26-07:00", 
    "direction": "Flat", 
    "sgv": 116, 
    "dateString": "2016-06-16T07:18:01-07:00", 
    "device": "openaps://cgm", 
    "unfiltered": 119296, 
    "rssi": 196, 
    "date": 1466086681000, 
    "filtered": 116560, 
    "type": "sgv", 
    "glucose": 116
  }, 
  {
    "trend_arrow": "FLAT", 
    "display_time": "2016-06-16T07:48:02-07:00", 
    "system_time": "2016-06-16T13:45:26-07:00", 
    "direction": "Flat", 
    "sgv": 114, 
    "dateString": "2016-06-16T07:48:02-07:00", 
    "device": "openaps://cgm", 
    "unfiltered": 125184, 
    "rssi": 196, 
    "date": 1466088482000, 
    "filtered": 125536, 
    "type": "sgv", 
    "glucose": 114
  }, 
  {
    "trend_arrow": "FLAT", 
    "display_time": "2016-06-16T07:43:01-07:00", 
    "system_time": "2016-06-16T13:40:26-07:00", 
    "direction": "Flat", 
    "sgv": 115, 
    "dateString": "2016-06-16T07:43:01-07:00", 
    "device": "openaps://cgm", 
    "unfiltered": 125568, 
    "rssi": 199, 
    "date": 1466088181000, 
    "filtered": 124784, 
    "type": "sgv", 
    "glucose": 115
  }, 
  {
    "trend_arrow": "FLAT", 
    "display_time": "2016-06-16T07:58:02-07:00", 
    "system_time": "2016-06-16T13:55:26-07:00", 
    "direction": "Flat", 
    "sgv": 112, 
    "dateString": "2016-06-16T07:58:02-07:00", 
    "device": "openaps://cgm", 
    "unfiltered": 121744, 
    "rssi": 444, 
    "date": 1466089082000, 
    "filtered": 124240, 
    "type": "sgv", 
    "glucose": 112
  }, 
  {
    "trend_arrow": "FLAT", 
    "display_time": "2016-06-16T07:53:01-07:00", 
    "system_time": "2016-06-16T13:50:26-07:00", 
    "direction": "Flat", 
    "sgv": 113, 
    "dateString": "2016-06-16T07:53:01-07:00", 
    "device": "openaps://cgm", 
    "unfiltered": 122352, 
    "rssi": 202, 
    "date": 1466088781000, 
    "filtered": 125360, 
    "type": "sgv", 
    "glucose": 113
  }, 
  {
    "trend_arrow": "FLAT", 
    "display_time": "2016-06-16T08:13:02-07:00", 
    "system_time": "2016-06-16T14:10:26-07:00", 
    "direction": "Flat", 
    "sgv": 105, 
    "dateString": "2016-06-16T08:13:02-07:00", 
    "device": "openaps://cgm", 
    "unfiltered": 118480, 
    "rssi": 186, 
    "date": 1466089982000, 
    "filtered": 120176, 
    "type": "sgv", 
    "glucose": 105
  }, 
  {
    "trend_arrow": "FLAT", 
    "display_time": "2016-06-16T08:08:01-07:00", 
    "system_time": "2016-06-16T14:05:26-07:00", 
    "direction": "Flat", 
    "sgv": 104, 
    "dateString": "2016-06-16T08:08:01-07:00", 
    "device": "openaps://cgm", 
    "unfiltered": 120304, 
    "rssi": 443, 
    "date": 1466089681000, 
    "filtered": 121184, 
    "type": "sgv", 
    "glucose": 104
  }, 
  {
    "trend_arrow": "FLAT", 
    "display_time": "2016-06-16T08:23:02-07:00", 
    "system_time": "2016-06-16T14:20:26-07:00", 
    "direction": "Flat", 
    "sgv": 100, 
    "dateString": "2016-06-16T08:23:02-07:00", 
    "device": "openaps://cgm", 
    "unfiltered": 114112, 
    "rssi": 444, 
    "date": 1466090582000, 
    "filtered": 117008, 
    "type": "sgv", 
    "glucose": 100
  }, 
  {
    "trend_arrow": "FLAT", 
    "display_time": "2016-06-16T08:18:01-07:00", 
    "system_time": "2016-06-16T14:15:26-07:00", 
    "direction": "Flat", 
    "sgv": 104, 
    "dateString": "2016-06-16T08:18:01-07:00", 
    "device": "openaps://cgm", 
    "unfiltered": 113936, 
    "rssi": 191, 
    "date": 1466090281000, 
    "filtered": 118912, 
    "type": "sgv", 
    "glucose": 104
  }, 
  {
    "trend_arrow": "FLAT", 
    "display_time": "2016-06-16T08:38:01-07:00", 
    "system_time": "2016-06-16T14:35:26-07:00", 
    "direction": "Flat", 
    "sgv": 94, 
    "dateString": "2016-06-16T08:38:01-07:00", 
    "device": "openaps://cgm", 
    "unfiltered": 110560, 
    "rssi": 426, 
    "date": 1466091481000, 
    "filtered": 112992, 
    "type": "sgv", 
    "glucose": 94
  }, 
  {
    "trend_arrow": "FLAT", 
    "display_time": "2016-06-16T08:28:01-07:00", 
    "system_time": "2016-06-16T14:25:26-07:00", 
    "direction": "Flat", 
    "sgv": 98, 
    "dateString": "2016-06-16T08:28:01-07:00", 
    "device": "openaps://cgm", 
    "unfiltered": 113424, 
    "rssi": 197, 
    "date": 1466090881000, 
    "filtered": 114864, 
    "type": "sgv", 
    "glucose": 98
  }, 
  {
    "trend_arrow": "FLAT", 
    "display_time": "2016-06-16T08:48:02-07:00", 
    "system_time": "2016-06-16T14:45:26-07:00", 
    "direction": "Flat", 
    "sgv": 96, 
    "dateString": "2016-06-16T08:48:02-07:00", 
    "device": "openaps://cgm", 
    "unfiltered": 105520, 
    "rssi": 177, 
    "date": 1466092082000, 
    "filtered": 108016, 
    "type": "sgv", 
    "glucose": 96
  }, 
  {
    "trend_arrow": "FLAT", 
    "display_time": "2016-06-16T08:43:01-07:00", 
    "system_time": "2016-06-16T14:40:26-07:00", 
    "direction": "Flat", 
    "sgv": 94, 
    "dateString": "2016-06-16T08:43:01-07:00", 
    "device": "openaps://cgm", 
    "unfiltered": 109120, 
    "rssi": 181, 
    "date": 1466091781000, 
    "filtered": 111600, 
    "type": "sgv", 
    "glucose": 94
  }, 
  {
    "trend_arrow": "FLAT", 
    "display_time": "2016-06-16T09:08:02-07:00", 
    "system_time": "2016-06-16T15:05:26-07:00", 
    "direction": "Flat", 
    "sgv": 108, 
    "dateString": "2016-06-16T09:08:02-07:00", 
    "device": "openaps://cgm", 
    "unfiltered": 112016, 
    "rssi": 177, 
    "date": 1466093282000, 
    "filtered": 107664, 
    "type": "sgv", 
    "glucose": 108
  }, 
  {
    "trend_arrow": "FLAT", 
    "display_time": "2016-06-16T09:03:01-07:00", 
    "system_time": "2016-06-16T15:00:26-07:00", 
    "direction": "Flat", 
    "sgv": 104, 
    "dateString": "2016-06-16T09:03:01-07:00", 
    "device": "openaps://cgm", 
    "unfiltered": 109328, 
    "rssi": 181, 
    "date": 1466092981000, 
    "filtered": 105792, 
    "type": "sgv", 
    "glucose": 104
  }, 
  {
    "trend_arrow": "FLAT", 
    "display_time": "2016-06-16T09:33:03-07:00", 
    "system_time": "2016-06-16T15:30:27-07:00", 
    "direction": "Flat", 
    "sgv": 119, 
    "dateString": "2016-06-16T09:33:03-07:00", 
    "device": "openaps://cgm", 
    "unfiltered": 131008, 
    "rssi": 182, 
    "date": 1466094783000, 
    "filtered": 125888, 
    "type": "sgv", 
    "glucose": 119
  }, 
  {
    "trend_arrow": "FLAT", 
    "display_time": "2016-06-16T09:33:03-07:00", 
    "system_time": "2016-06-16T15:30:27-07:00", 
    "direction": "Flat", 
    "sgv": 122, 
    "dateString": "2016-06-16T09:33:03-07:00", 
    "device": "openaps://cgm", 
    "unfiltered": 127584, 
    "rssi": 163, 
    "date": 1466094783000, 
    "filtered": 122256, 
    "type": "sgv", 
    "glucose": 122
  }, 
  {
    "trend_arrow": "FLAT", 
    "display_time": "2016-06-16T09:28:01-07:00", 
    "system_time": "2016-06-16T15:25:25-07:00", 
    "direction": "Flat", 
    "sgv": 120, 
    "dateString": "2016-06-16T09:28:01-07:00", 
    "device": "openaps://cgm", 
    "unfiltered": 124368, 
    "rssi": 176, 
    "date": 1466094481000, 
    "filtered": 118768, 
    "type": "sgv", 
    "glucose": 120
  }, 
  {
    "trend_arrow": "FLAT", 
    "display_time": "2016-06-16T09:43:03-07:00", 
    "system_time": "2016-06-16T15:40:27-07:00", 
    "direction": "Flat", 
    "sgv": 114, 
    "dateString": "2016-06-16T09:43:03-07:00", 
    "device": "openaps://cgm", 
    "unfiltered": 131040, 
    "rssi": 190, 
    "date": 1466095383000, 
    "filtered": 131424, 
    "type": "sgv", 
    "glucose": 114
  }, 
  {
    "trend_arrow": "FLAT", 
    "display_time": "2016-06-16T09:38:01-07:00", 
    "system_time": "2016-06-16T15:35:25-07:00", 
    "direction": "Flat", 
    "sgv": 117, 
    "dateString": "2016-06-16T09:38:01-07:00", 
    "device": "openaps://cgm", 
    "unfiltered": 132800, 
    "rssi": 178, 
    "date": 1466095081000, 
    "filtered": 129152, 
    "type": "sgv", 
    "glucose": 117
  }, 
  {
    "trend_arrow": "FLAT", 
    "display_time": "2016-06-16T10:33:01-07:00", 
    "system_time": "2016-06-16T16:30:25-07:00", 
    "direction": "Flat", 
    "sgv": 109, 
    "dateString": "2016-06-16T10:33:01-07:00", 
    "device": "openaps://cgm", 
    "unfiltered": 105440, 
    "rssi": 184, 
    "date": 1466098381000, 
    "filtered": 103088, 
    "type": "sgv", 
    "glucose": 109
  }, 
  {
    "trend_arrow": "FLAT", 
    "display_time": "2016-06-16T10:23:01-07:00", 
    "system_time": "2016-06-16T16:20:25-07:00", 
    "direction": "Flat", 
    "sgv": 86, 
    "dateString": "2016-06-16T10:23:01-07:00", 
    "device": "openaps://cgm", 
    "unfiltered": 101472, 
    "rssi": 183, 
    "date": 1466097781000, 
    "filtered": 105936, 
    "type": "sgv", 
    "glucose": 86
  }, 
  {
    "trend_arrow": "FLAT", 
    "display_time": "2016-06-16T11:43:02-07:00", 
    "system_time": "2016-06-16T17:40:27-07:00", 
    "direction": "Flat", 
    "sgv": 220, 
    "dateString": "2016-06-16T11:43:02-07:00", 
    "device": "openaps://cgm", 
    "unfiltered": 213056, 
    "rssi": 190, 
    "date": 1466102582000, 
    "filtered": 209856, 
    "type": "sgv", 
    "glucose": 220
  }, 
  {
    "trend_arrow": "FLAT", 
    "display_time": "2016-06-16T11:43:02-07:00", 
    "system_time": "2016-06-16T17:40:27-07:00", 
    "direction": "Flat", 
    "sgv": 220, 
    "dateString": "2016-06-16T11:43:02-07:00", 
    "device": "openaps://cgm", 
    "unfiltered": 212800, 
    "rssi": 169, 
    "date": 1466102582000, 
    "filtered": 205792, 
    "type": "sgv", 
    "glucose": 220
  }, 
  {
    "trend_arrow": "45_UP", 
    "display_time": "2016-06-16T11:38:00-07:00", 
    "system_time": "2016-06-16T17:35:25-07:00", 
    "direction": "FortyFiveUp", 
    "sgv": 216, 
    "dateString": "2016-06-16T11:38:00-07:00", 
    "device": "openaps://cgm", 
    "unfiltered": 209408, 
    "rssi": 185, 
    "date": 1466102280000, 
    "filtered": 201824, 
    "type": "sgv", 
    "glucose": 216
  }, 
  {
    "trend_arrow": "FLAT", 
    "display_time": "2016-06-16T11:53:00-07:00", 
    "system_time": "2016-06-16T17:50:25-07:00", 
    "direction": "Flat", 
    "sgv": 218, 
    "dateString": "2016-06-16T11:53:00-07:00", 
    "device": "openaps://cgm", 
    "unfiltered": 211680, 
    "rssi": 180, 
    "date": 1466103180000, 
    "filtered": 213472, 
    "type": "sgv", 
    "glucose": 218
  }, 
  {
    "trend_arrow": "FLAT", 
    "display_time": "2016-06-16T11:48:00-07:00", 
    "system_time": "2016-06-16T17:45:25-07:00", 
    "direction": "Flat", 
    "sgv": 218, 
    "dateString": "2016-06-16T11:48:00-07:00", 
    "device": "openaps://cgm", 
    "unfiltered": 211648, 
    "rssi": 191, 
    "date": 1466102880000, 
    "filtered": 212704, 
    "type": "sgv", 
    "glucose": 218
  }
]